magicbits/__init__.py
magicbits/ds/__init__.py
magicbits/ds/binarytree.py
magicbits/ds/doublell.py
magicbits/ds/graph.py
magicbits/ds/infix.py
magicbits/ds/ll.py
magicbits/ds/nqueue.py
magicbits/ds/pqueue.py
magicbits/ds/stack1.py
magicbits/ds/stack2.py
magicbits/lap/__init__.py
magicbits/lap/complex.py
magicbits/lap/eigen.py
magicbits/lap/factors.py
magicbits/lap/gcd.py
magicbits/lap/matrixinv.py
magicbits/lap/matrixmulti.py
magicbits/lap/matrixtranspose.py
magicbits/lap/opprojection.py
magicbits/lap/ref.py
magicbits/lap/scattermulti.py
magicbits/lap/scattersingle.py
magicbits/os/__init__.py
magicbits/os/factorial.py
magicbits/os/fcfs.py
magicbits/os/fibonacci.py
magicbits/os/fifo.py
magicbits/os/filesystem.py
magicbits/os/lru.py
magicbits/os/rr.py
magicbits/os/rw.py
magicbits/os/sjf.py
magicbits/os/threads.py
magicbits-3.0.1.dist-info/METADATA
magicbits-3.0.1.dist-info/WHEEL
magicbits-3.0.1.dist-info/top_level.txt
magicbits-3.0.1.dist-info/RECORD
