Metadata-Version: 2.1
Name: magicbits
Version: 3.0.1
Summary: A simple package for demostration of concept of OS in python
Home-page: UNKNOWN
Author: Stella Ruth
Author-email: stella.ruth7672@proton.me
License: UNKNOWN
Keywords: os cpu scheduling
Platform: UNKNOWN
Classifier: License :: OSI Approved :: MIT License
Classifier: Environment :: Web Environment
Classifier: Intended Audience :: Developers
Classifier: Natural Language :: English
Classifier: Operating System :: OS Independent
Classifier: Programming Language :: Python :: 3.8
Classifier: Programming Language :: Python :: 3.7
Classifier: Programming Language :: Python :: 3.6
Requires-Dist: tabulate >=0.9.0
Requires-Dist: matplotlib >=3.8.0
Requires-Dist: numpy >=1.26.1
